[
    {"id":1, 
      "title": "Groceries",
      "desc": "Milk, Meat, Fruits and Vegetable etc",
      "icon1": "fa-cow",
      "icon2": "fa-apple-whole",
      "icon3": "fa-drumstick-bite",
      "label": "Total Spend",
      "amount": "4,678.00",
      "color": "#4CAF50"
    },
    {"id":2, 
      "title": "Transportation",
      "desc": "Fuel, Bus, Train etc",
      "icon1": "fa-gas-pump",
      "icon2": "fa-bus",
      "icon3": "fa-train",
      "label": "Total Spend",
      "amount": "8,675.00",
      "color": "#D88913"
    },
    {"id":3, 
      "title": "Food",
      "desc": "Dineout, Swiggy, Zomato etc",
      "icon1": "fa-burger",
      "icon2": "fa-bottle-droplet",
      "icon3": "fa-fish",
      "label": "Total Spend",
      "amount": "5,375.00",
      "color": "#E45F5F"
    },
    {"id":4, 
      "title": "Fun",
      "desc": "Leisure and other Fun activities",
      "icon1": "fa-film",
      "icon2": "fa-location-dot",
      "icon3": "fa-fire",
      "label": "Total Spend",
      "amount": "3,879.00",
      "color": "#E91E63"
    },
    {"id":5, 
      "title": "Healthcare",
      "desc": "Medical Insurance, Doctor Visits etc",
      "icon1": "fa-stethoscope",
      "icon2": "fa-syringe",
      "icon3": "fa-circle-h",
      "label": "Total Spend",
      "amount": " 12,879.00",
      "color": "#009688"
    },
    {"id":6, 
      "title": "Utilities",
      "desc": "Internet, Electricity, Water, Gas etc",
      "icon1": "fa-wifi",
      "icon2": "fa-lightbulb",
      "icon3": "fa-droplet",
      "label": "Total Spend",
      "amount": "3,879.00",
      "color": "#3F51B5"
    },
    {"id":7, 
      "title": "Misc",
      "desc": "Any other spending you may have",
      "icon1": "fa-list-check",
      "icon2": "fa-credit-card",
      "icon3": "fa-wallet",
      "label": "Total Spend",
      "amount": "230.000",
      "color": "#795548"
    }
  ]